<annotation>
	<folder></folder>
	<filename>25-08-2023130348_jpg.rf.6c5b3fc4b6aeb9edf7610e4485ce0216.jpg</filename>
	<path>25-08-2023130348_jpg.rf.6c5b3fc4b6aeb9edf7610e4485ce0216.jpg</path>
	<source>
		<database>roboflow.com</database>
	</source>
	<size>
		<width>640</width>
		<height>640</height>
		<depth>3</depth>
	</size>
	<segmented>0</segmented>
	<object>
		<name>ym</name>
		<pose>Unspecified</pose>
		<truncated>0</truncated>
		<difficult>0</difficult>
		<occluded>0</occluded>
		<bndbox>
			<xmin>222</xmin>
			<xmax>231</xmax>
			<ymin>454</ymin>
			<ymax>464</ymax>
		</bndbox>
	</object>
	<object>
		<name>ym</name>
		<pose>Unspecified</pose>
		<truncated>0</truncated>
		<difficult>0</difficult>
		<occluded>0</occluded>
		<bndbox>
			<xmin>233</xmin>
			<xmax>244</xmax>
			<ymin>549</ymin>
			<ymax>563</ymax>
		</bndbox>
	</object>
	<object>
		<name>ym</name>
		<pose>Unspecified</pose>
		<truncated>0</truncated>
		<difficult>0</difficult>
		<occluded>0</occluded>
		<bndbox>
			<xmin>360</xmin>
			<xmax>374</xmax>
			<ymin>216</ymin>
			<ymax>234</ymax>
		</bndbox>
	</object>
	<object>
		<name>ym</name>
		<pose>Unspecified</pose>
		<truncated>0</truncated>
		<difficult>0</difficult>
		<occluded>0</occluded>
		<bndbox>
			<xmin>389</xmin>
			<xmax>399</xmax>
			<ymin>358</ymin>
			<ymax>376</ymax>
		</bndbox>
	</object>
	<object>
		<name>ym</name>
		<pose>Unspecified</pose>
		<truncated>0</truncated>
		<difficult>0</difficult>
		<occluded>0</occluded>
		<bndbox>
			<xmin>331</xmin>
			<xmax>337</xmax>
			<ymin>351</ymin>
			<ymax>362</ymax>
		</bndbox>
	</object>
</annotation>
